django_pg_bulk_update/__init__.py
django_pg_bulk_update/clause_operators.py
django_pg_bulk_update/compatibility.py
django_pg_bulk_update/manager.py
django_pg_bulk_update/query.py
django_pg_bulk_update/set_functions.py
django_pg_bulk_update/types.py
django_pg_bulk_update/utils.py
django_pg_bulk_update-3.7.3.dist-info/LICENSE
django_pg_bulk_update-3.7.3.dist-info/METADATA
django_pg_bulk_update-3.7.3.dist-info/WHEEL
django_pg_bulk_update-3.7.3.dist-info/top_level.txt
django_pg_bulk_update-3.7.3.dist-info/RECORD
