Metadata-Version: 2.1
Name: django-pg-bulk-update
Version: 3.7.3
Summary: Django extension, executing bulk update operations for PostgreSQL
Home-page: https://github.com/M1hacka/django-pg-bulk-update
Author: Mikhail Shvein
Author-email: work_shvein_mihail@mail.ru
License: BSD 3-clause "New" or "Revised" License
License-File: LICENSE
Requires-Dist: django >=1.7
Requires-Dist: pytz ; python_version < "3.3"
Requires-Dist: typing ; python_version < "3.5"
